gvaspythonlib/__init__.py
gvaspythonlib/my_functions.py
gvaspythonlib-0.1.0.dist-info/METADATA
gvaspythonlib-0.1.0.dist-info/WHEEL
gvaspythonlib-0.1.0.dist-info/top_level.txt
gvaspythonlib-0.1.0.dist-info/RECORD
